{
  "name": "Норі",
  "icon": "sushigocrafting:nori_sheets",
  "category": "sushigocrafting:getting_started",
  "sortnum": 2,
  "read_by_default": false,
  "pages": [
    {
      "type": "text",
      "text": "Щоб отримати листи норі, вам потрібно знайти в океані морські водорості й зробити з них блок висушених морських водоростей. $(br2)Розчавивши блок висушених морських водоростей між залізним блоком і поршнем, ви отримаєте листи норі."
    },
    {
      "type": "image",
      "images": [
        "sushigocrafting:textures/gui/book/nori.png"
      ],
      "text": "Поршневе приготування норі"
    }
  ]
}